{
  "menu": [
    {
      "id": 1,
      "name": "Pasta",
      "image": "./images/pasta.jpg",
      "price": 15.99
    },
    {
      "id": 2,
      "name": "Green Salad",
      "image": "./images/green-salad.jpg",
      "price": 7.99
    },
    {
      "id": 3,
      "name": "Cheese Pizza",
      "image": "./images/cheese-pizza.jpg",
      "price": 12.99
    },
    {
      "id": 4,
      "name": "Tomato Soup",
      "image": "./images/tomato-soup.jpg",
      "price": 13.99
    },
    {
      "id": 5,
      "name": "Chicken Sandwich",
      "image": "./images/chicken-sandwich.jpg",
      "price": 7.99
    },
    {
      "id": 6,
      "name": "Bacon Cheeseburger",
      "image": "./images/bacon-cheeseburger.jpg",
      "price": 10.99
    }
  ],
  "reviews": [
    {
      "name": "Groov",
      "content": "dads",
      "id": 1
    },
    {
      "name": "",
      "content": "",
      "id": 2
    },
    {
      "name": "HEllo",
      "content": "Great!",
      "id": 3
    },
    {
      "name": "Hello",
      "content": "Grweat!\n",
      "id": 4
    },
    {
      "name": "Bob",
      "content": "Terrific!",
      "id": 5
    },
    {
      "name": "Billy",
      "content": "Great!\n",
      "id": 6
    },
    {
      "name": "Greg",
      "content": "Not good",
      "id": 7
    },
    {
      "name": "",
      "content": "",
      "id": 8
    },
    {
      "name": "Toom",
      "content": "Good",
      "id": 9
    },
    {
      "name": "Steve",
      "content": "Bad\n",
      "id": 10
    },
    {
      "name": "Michale",
      "content": "Poor",
      "id": 11
    },
    {
      "name": "Greg",
      "content": "Awesome!",
      "id": 12
    },
    {
      "name": "Greg",
      "content": "Super!",
      "id": 13
    },
    {
      "name": "Tom",
      "content": "Super",
      "id": 14
    },
    {
      "name": "Tony",
      "content": "Super",
      "id": 15
    },
    {
      "name": "T?remend",
      "content": "dasds",
      "id": 16
    }
  ]
}